{"general":{"position":"ეკონომიკური დეპარტამენტის მატერიალურ-ტექნიკური უზრუნველყოფის სამმართველოს შტატგარეშე მოსამსახურე (ცეცხლფარეში)","provided_by":"განათლებისა და მეცნიერების სამინისტრო","category":"მომსახურება","deadline":"2012/11/29","salary":"შეთანხმებით","num_positions":"1","location":"თბილისი","job_type":"სრული განაკვეთი","probation_period":"გამოსაცდელი ვადის გარეშე","vacancy_id":"1119"},"contact":{"address":null,"phone":"2318940","contact_person":"ნინო გაბრიელაშვილი"},"job_description":"არასამუშაო საათებში და დასვენების დღეებში საქვაბის გამართული და უსაფრთხო მუშაობის ზედამხედველობა და უზრუნველყოფა (განსაკუთრებულ შემთხვევაში დღის განმავლობაშიც).","additional_requirements":"საქვაბეების მოწყობილობის, ცენტრალური და ცილინდრული ტიპის ტუმბოების მოწყობილობისა და მუშაობის, ელექტროძრავების მუშაობის პრინციპის, საკონტროლო-გამზომი ხელსაწყოების მოწყობილობისა  და მუშაობის პრინციპების ცოდნა.","additional_info":"არ არის მითითებული","qualifications":{"degree":null,"work_experience":"3 წელი","profession":"ინჟინერ მექანიკოსი","age":"21 დან - 65 მდე","knowledge_legal_acts":null},"computers":[],"languages":[]}