{"general":{"position":"ბორჯომის მუნიციპალიტეტის ყვიბისის ტერიტორიული ორგანოს რწმუნებული","provided_by":"ბორჯომის მუნიციპალიტეტის საკრებულო","category":"ადგილობრივი თვითმმართველობა","deadline":"2013/04/17","salary":"700 ლარიდან - 1000 ლარამდე","num_positions":"1","location":"ბორჯომი","job_type":"სრული განაკვეთი","probation_period":"3 თვე","vacancy_id":"2465"},"contact":{"address":"ქ. ბორჯომი, მესხეთის ქ. #5","phone":"995 367 22 13 66. mob. 599 94 28 55","contact_person":"იოსებ სარალიძე"},"job_description":"გამგეობის ტერიტორიული ორგანოს საქმიანობის მართვა","additional_requirements":"კონკურსში მონაწილე კანდიდატს უნდა გააჩნდეს ქართულ ენაზე ზეპირი და წერილობითი კომუნიკაციის უნარი. ანალიზისა და ლოგიკური აზროვნების, გუნდური მუშაობის, დროის სწორად გადანაწილების უნარი; პუნქტუალურობა, ორგანიზებულობა, შრომისმოყვარეობა, პასუხისმგებლობა, კომუნიკაბელურობა.","additional_info":"კონკურსანტს უფლება აქვს განაცხადი შეიტანოს ბორჯომის მუნიციპალიტეტის მიერ გამოცხადებულ მხოლოდ ერთ ვაკანტურ თანამდეობაზე","qualifications":{"degree":"ბაკალავრი","work_experience":"1 წელი","profession":null,"age":"25 დან - 65 მდე","knowledge_legal_acts":"1.\tსაქართველოს კონსტიტუცია\n2.\tსაქართველოს ორგანული კანონი „ადგილობრივი თვითმმართველობის შესახებ“\n3.\tსაქართველოს კანონი „საჯარო სამსახურის შესახებ“\n4.\tსაქართველოს პრეზიდენტის 1999 წლის 1 ივლისის #414 ბრძანებულება „საქმისწარმოების ერთიანი წესების დამტკიცებისა და ამოქმედების შესახებ“"},"computers":[{"program":"Microsoft Office Word","knowledge":"ძალიან კარგი"},{"program":"Microsoft Office Excel","knowledge":"ძალიან კარგი"},{"program":"ინტერნეტი","knowledge":"ძალიან კარგი"}],"languages":[{"language":"ქართული","writing":"ძალიან კარგი","reading":"ძალიან კარგი"}]}