{"general":{"position":"Not Indicated","provided_by":"Georgain State Hydrographic Service","category":"Secretary/Office Management","deadline":"2014/05/14","salary":"1025 GEL","num_positions":"1","location":"Foti","job_type":"Full Time","probation_period":"Without probation period","vacancy_id":"15156"},"contact":{"address":"ქ. ფოთი თავდადებულის 93","phone":"577950012","contact_person":"ნინო ნებიერიძე"},"job_description":"სამსახურის დირექტორის ყოველდღიური საქმიანობის ორგანიზება და მიმდინარე დავალებების შესრულება; სატელეფონო ზარებზე პასუხების გაცემა; სამუშაო შეხვედრების დაგეგმვა;პარტნიორ და ადგილობრივ ორგანიზაციებთან კორესპონდენციის მიმოცვლა;","additional_requirements":"სასურველია უმაღლესი განათლება მენეჯმენტის და ადმინისტრირების განხრით.","additional_info":"კონკურსის ეტაპებია:\n1)საკვალიფიკაციო მონაცემების განხილვა;\n2) გასაუბრება (ინგლისურ და რუსულ ენაზე).","qualifications":{"degree":"Higher Education","work_experience":"1 year","profession":"Secretery/Receptionist","age":"21 From","knowledge_legal_acts":null},"computers":[{"program":"Microsoft Office Word","knowledge":"Very Good"},{"program":"Microsoft Office Excel","knowledge":"Very Good"},{"program":"Microsoft Office Outlook","knowledge":"Very Good"},{"program":"Internet","knowledge":"Very Good"}],"languages":[{"language":"Georgian","writing":"Very Good","reading":"Very Good"},{"language":"English","writing":"Very Good","reading":"Very Good"},{"language":"Russian","writing":"Good","reading":"Good"}]}