{"general":{"position":"სოფელ ციხისჯვრის ტერიტორიული ორგანოს სპეციალისტი","provided_by":"ბორჯომის მუნიციპალიტეტის საკრებულო","category":"ადგილობრივი თვითმმართველობა","deadline":"2014/02/28","salary":"450 ლარი","num_positions":"1","location":"არ არის მითითებული","job_type":"სრული განაკვეთი","probation_period":"3 თვე","vacancy_id":"13118"},"contact":{"address":"ქ. ბორჯომი, მესხეთის ქ. #5","phone":"599 22 17 25","contact_person":"ნათელა გოგოლაძე"},"job_description":"უზრუნველყოფს ადმინისტრაციული ერთულის მოსახლეობის კავშირს საკრებულოსთან, გამგეობასთან და ადგილობრივი თვითმმართველობის თანამდებობის პირებთან. ექვემდებარება ტერიტორიული ორგანოს რწმუნებულს\nაწარმოებენ სტატისტიკურ და სხვა მონაცემთა შეგროვებას. ადგილობრივი თვითმმართველობის სამართლებრივი აქტების გაცნობას მოსახლეობასთან. გასცემს ცნობებს მოსახლეობაზე კანონით მინიჭებული წესით.","additional_requirements":"კონკურსანტს უფლება აქვს განაცხადი შეავსოს ბორჯომის მუნიციპალიტეტის მიერ გამოცხადებულ მხოლოდ ერთ ვაკანტურ თანამდებობაზე","additional_info":"კონკურსი ჩატარდება ორ ეტაპად:\n1. წარმოდგენილი განცხადებისა და დოკუმენტაციის შესწავლა\n2. გასაუბრება","qualifications":{"degree":"საშუალო სკოლა დამთავრებული","work_experience":null,"profession":null,"age":"18 დან","knowledge_legal_acts":"საქართველოს ორგანული კანონი \"ადგილობრივი თვითმმართველობის შესახებ\" - ზოგადი ცოდნა\nტერიტორიული ორგანოს რწმუნებულის დებულება - ზოგადი ცოდნა"},"computers":[{"program":"Microsoft Office Word","knowledge":"კარგი"},{"program":"Microsoft Office Excel","knowledge":"კარგი"},{"program":"ინტერნეტი","knowledge":"კარგი"}],"languages":[{"language":"ქართული","writing":"ძალიან კარგი","reading":"ძალიან კარგი"}]}