{"general":{"position":"შესყიდვების კოორდინატორი","provided_by":"სსიპ საქართველოს სტანდარტებისა და მეტროლოგიის ეროვნული სააგენტო","category":"შესყიდვები","deadline":"2013/11/15","salary":"600 ლარიდან - 800 ლარამდე","num_positions":"1","location":"არ არის მითითებული","job_type":"სრული განაკვეთი","probation_period":"გამოსაცდელი ვადის გარეშე","vacancy_id":"7481"},"contact":{"address":"ჩარგლის 67","phone":"261 35 00","contact_person":"თ. პეტაშვილი"},"job_description":"სახელმწიფო ბიუჯეტით განსაზღვრული ასიგნებების ფარგლებში \"სახელმწიფო შესყიდვების შესახებ\" საქართველოს კანონის შესაბამისად სააგენტოს საჭიროებისათვის საქონლის, მომსახურებისა და სამუშაოთა შესყიდვების დაგეგმვა, ორგანიზაცია და განხორციელება; განხორციელებული შესყიდვების მონიტორინგისა და კონტროლის უზრუნველყოფა, კანონით გათვალისწინებული ანგარიშგების წარმოება.","additional_requirements":"არ არის მითითებული","additional_info":"კონკურსი ჩატარდება გასაუბრების ფორმით;\nკონკურსში მონაწილეობას მიიღებს მხოლოდ ის კანდიდატი, რომელიც განაცხადის გადარჩევის საფუძველზე დააკმაყოფილებს დადგენილ საკვალიფიკაციო მოთხოვნებს.","qualifications":{"degree":"მაგისტრი","work_experience":null,"profession":"ეკონომისტი","age":"21 დან - 65 მდე","knowledge_legal_acts":null},"computers":[{"program":"Microsoft Office Word","knowledge":"ძალიან კარგი"},{"program":"Microsoft Office Excel","knowledge":"ძალიან კარგი"},{"program":"Microsoft Office PowerPoint","knowledge":"ძალიან კარგი"},{"program":"Microsoft Office Outlook","knowledge":"ძალიან კარგი"}],"languages":[{"language":"ქართული","writing":"ძალიან კარგი","reading":"ძალიან კარგი"},{"language":"ინგლისური","writing":"ძალიან კარგი","reading":"ძალიან კარგი"},{"language":"რუსული","writing":"ძალიან კარგი","reading":"ძალიან კარგი"}]}