{"general":{"position":"მეტროლოგიის ინსტიტუტის მასისა და მასასთან დაკავშირებული სიდიდეების განყოფილების სპეციალისტი","provided_by":"სსიპ საქართველოს სტანდარტებისა და მეტროლოგიის ეროვნული სააგენტო","category":"ტექნიკური სამუშაოები","deadline":"2013/06/09","salary":"290 ლარი","num_positions":"1","location":"თბილისი","job_type":"სრული განაკვეთი","probation_period":"გამოსაცდელი ვადის გარეშე","vacancy_id":"3555"},"contact":{"address":"ქ. თბილისი, ჩარგლის ქ. N67","phone":"2606621","contact_person":"ეკა ლაბაძე"},"job_description":"1. ეტალონებისა და გაზომვის საშუალებების ექსპლუატაციისა და კვლევების საჭირო პირობების დაცვა;\n2. გაზმოვების მონაცემების დაგროვება, სტატისტიკური დამუშავება და ანალიზი;\n3. პროფილაქტიკური ღონისძიებების ჩატარება ეტალონების სტაბილურობისა და მეტროლოგიური მახასიათებლების შენარჩუნების მიზნით;\n4. ეტალონებისა და გაზომვის საშუალებების გაკვლევადობის. დაკალიბრება/დამოწმების და შუალედური შემოწმებების ჩატარება;\n5. ეტალონებისა და გაზომვის საშუალებების დაკალიბრების პროცედურებისა და განუსაზღვრელობის ბიუჯეტის შემუშავება;\n6. ეტალონებისა და გაზომვის საშუალებების დაკალიბრებისა და დამოწმების სამუშაოების ჩატარება.","additional_requirements":"არ არის მითითებული","additional_info":"არ არის მითითებული","qualifications":{"degree":"ბაკალავრი","work_experience":"2 წელი","profession":"ტექნიკური","age":"21 დან - 65 მდე","knowledge_legal_acts":"1. პროდუქტის უსაფრთხოებისა და თავისუფალი მიმოქცევის კოდექსი;\n2. ,,სსიპ საქართველოს სტანდარტებისა და მეტროლოგიის ეროვნული სააგენტოს დებულების დამტკიცების შესახებ\" საქართველოს ეკონომიკისა და მდგრადი განვითარების მინისტრის 2012 წლის 26 ივლისის N1/1570 ბრძანება"},"computers":[{"program":"Microsoft Office Word","knowledge":"კარგი"},{"program":"Microsoft Office Excel","knowledge":"კარგი"},{"program":"MS office applications","knowledge":"კარგი"},{"program":"Adobe Acrobat","knowledge":"კარგი"}],"languages":[{"language":"რუსული","writing":"კარგი","reading":"კარგი"},{"language":"ინგლისური","writing":"კარგი","reading":"კარგი"}]}