{"general":{"position":"Programmer","provided_by":"Civil Service Bureau","category":"Programming","deadline":"2013/06/05","salary":"1000 GEL","num_positions":"1","location":"Tbilisi","job_type":"Full Time","probation_period":"Without probation period","vacancy_id":"3200"},"contact":{"address":"ინგოროყვას 7","phone":"2192928","contact_person":null},"job_description":"• ბიუროს ვებ-გვერდების მუდმივი მონიტორინგი;\n• ვებ-გვერდის დახვეწა და განვითარება;\n• ტექნიკური ხარვეზების დროული აღმოჩენა და მისი აღმოფხვრის უზრუნველყოფა საკუთარი ძალებით, ან პასუხისმგებელი კოლეგის დროუილი ინფორმირება;\n• ბიუროს ვებ-გვერდების კონტენტ მენეჯმენტი;\n• ხელმძღვანელობის მხრიდან სხვა დავალებების შესრულება.","additional_requirements":"- თანამედროვე ტექნოლოგიების კარგი ცოდნა;\n- გამართულად წერის უნარი;\n- კომუნიკაბელურობა;\n- ლოგიკური აზროვნება; \n- სტრესულ გარემოში მუშაობის უნარი;\n- ორგანიზებულობა და დეტალებზე ორიენტირებულობა.","additional_info":"წარმატებული კანდიდატის შერჩევა მოხდება ორ ეტაპად:\n1.  აპლიკაციების გადარჩევა;\n2.  გასაუბრება.","qualifications":{"degree":"Bachelor's Degree","work_experience":"2 years","profession":"Programmer","age":null,"knowledge_legal_acts":null},"computers":[{"program":"PHP","knowledge":"Very Good"},{"program":"MYSQL","knowledge":"Very Good"},{"program":"HTML","knowledge":"Very Good"},{"program":"CSS","knowledge":"Very Good"},{"program":"JavaScript","knowledge":"Very Good"},{"program":"jQuery","knowledge":"Very Good"}],"languages":[{"language":"English","writing":"Good","reading":"Good"}]}