{"general":{"position":"Specialist at KartikamiTerritorial Authority (Takhcha)","provided_by":"Akhalkalaki Municipality Assembly","category":"Local Government","deadline":"2014/05/04","salary":"550 GEL","num_positions":"1","location":"Akhalqalaqi","job_type":"Full Time","probation_period":"Without probation period","vacancy_id":"14888"},"contact":{"address":"ქ.ახალქალაქი მაშტოცის ქ.33","phone":"599417941","contact_person":"გოარიკ აკოპიან"},"job_description":"უზრუნველყოფს ადმინისტრაციული ერთეულის მოსახლეობის კავშირს საკრებულოსთან,გამგეობასთან და ადგილობრივი თვითმმართველობის თანამდებობის პირებთან.ექვემდებარება ტერიტორიული ორგანოს რწმუნებულს აწარმოებს სტატისტიკურ და სხვა მონაცემთა შეგროვებას.ადგილობრივი თვითმმართველობის სამართლებრივი აქტების გაცნობას მოსახლეობასთან.გასცემს ცნობებს მოსახლეობაზე კანონით მინიჭებული წესით.","additional_requirements":"Not Indicated","additional_info":"კონკურსი ჩატარდება ორ ეტაპად\n1.აპლიკაციების შეფასება/გადარჩევა\n2.გასაუბრება","qualifications":{"degree":"High School Graduate","work_experience":"1 year","profession":null,"age":"18 From","knowledge_legal_acts":"-”ადგილობრივი თვითმმართველობის შესახებ“ საქართველოს ორგანული კანონი;\n-„საჯარო სამსახურის შესახებ“  საქართველოს კანონი;\n-ზოგადი ადმინისტრაციული კოდექსი\"."},"computers":[{"program":"Microsoft Office Word","knowledge":"Good"},{"program":"Microsoft Office Excel","knowledge":"Good"},{"program":"Internet Explorer","knowledge":"Good"}],"languages":[{"language":"Georgian","writing":"Very Good","reading":"Very Good"},{"language":"Armenian","writing":"Good","reading":"Good"}]}